apache_airflow_providers_edge/__init__.py
apache_airflow_providers_edge/telemetry.py
apache_airflow_providers_edge-2.10.0.dist-info/METADATA
apache_airflow_providers_edge-2.10.0.dist-info/WHEEL
apache_airflow_providers_edge-2.10.0.dist-info/top_level.txt
apache_airflow_providers_edge-2.10.0.dist-info/RECORD
